tempest/README.rst
tempest/__init__.py
tempest/clients.py
tempest/config.py
tempest/exceptions.py
tempest/test.py
tempest/version.py
tempest/api/README.rst
tempest/api/__init__.py
tempest/api/compute/__init__.py
tempest/api/compute/api_microversion_fixture.py
tempest/api/compute/base.py
tempest/api/compute/test_extensions.py
tempest/api/compute/test_networks.py
tempest/api/compute/test_quotas.py
tempest/api/compute/test_tenant_networks.py
tempest/api/compute/test_versions.py
tempest/api/compute/admin/__init__.py
tempest/api/compute/admin/test_aggregates_negative.py
tempest/api/compute/admin/test_assisted_volume_snapshots.py
tempest/api/compute/admin/test_auto_allocate_network.py
tempest/api/compute/admin/test_availability_zone.py
tempest/api/compute/admin/test_availability_zone_negative.py
tempest/api/compute/admin/test_create_server.py
tempest/api/compute/admin/test_delete_server.py
tempest/api/compute/admin/test_flavors.py
tempest/api/compute/admin/test_flavors_access.py
tempest/api/compute/admin/test_flavors_access_negative.py
tempest/api/compute/admin/test_flavors_extra_specs.py
tempest/api/compute/admin/test_flavors_extra_specs_negative.py
tempest/api/compute/admin/test_flavors_microversions.py
tempest/api/compute/admin/test_hosts.py
tempest/api/compute/admin/test_hosts_negative.py
tempest/api/compute/admin/test_hypervisor.py
tempest/api/compute/admin/test_hypervisor_negative.py
tempest/api/compute/admin/test_instance_usage_audit_log.py
tempest/api/compute/admin/test_instance_usage_audit_log_negative.py
tempest/api/compute/admin/test_keypairs_v210.py
tempest/api/compute/admin/test_live_migration.py
tempest/api/compute/admin/test_live_migration_negative.py
tempest/api/compute/admin/test_migrations.py
tempest/api/compute/admin/test_networks.py
tempest/api/compute/admin/test_quotas.py
tempest/api/compute/admin/test_quotas_negative.py
tempest/api/compute/admin/test_security_groups.py
tempest/api/compute/admin/test_server_diagnostics.py
tempest-46.0.0.dist-info/AUTHORS
tempest-46.0.0.dist-info/LICENSE
tempest-46.0.0.dist-info/METADATA
tempest-46.0.0.dist-info/WHEEL
tempest-46.0.0.dist-info/entry_points.txt
tempest-46.0.0.dist-info/pbr.json
tempest-46.0.0.dist-info/top_level.txt
tempest-46.0.0.dist-info/RECORD
