Metadata-Version: 2.1
Name: tempest
Version: 46.0.0
Summary: OpenStack Integration Testing
Home-page: https://docs.openstack.org/tempest/latest/
Author: OpenStack
Author-email: openstack-discuss@lists.openstack.org
Classifier: Intended Audience :: Information Technology
Classifier: Intended Audience :: System Administrators
Classifier: Intended Audience :: Developers
Classifier: License :: OSI Approved :: Apache Software License
Classifier: Operating System :: POSIX :: Linux
Classifier: Programming Language :: Python
Classifier: Programming Language :: Python :: 3
Classifier: Programming Language :: Python :: 3.10
Classifier: Programming Language :: Python :: 3.11
Classifier: Programming Language :: Python :: 3.12
Classifier: Programming Language :: Python :: 3.13
Classifier: Programming Language :: Python :: 3 :: Only
Classifier: Programming Language :: Python :: Implementation :: CPython
License-File: LICENSE
License-File: AUTHORS
Requires-Dist: pbr !=2.1.0,>=2.0.0
Requires-Dist: cliff !=2.9.0,>=2.8.0
Requires-Dist: jsonschema >=3.2.0
Requires-Dist: testtools >=2.2.0
Requires-Dist: paramiko >=2.7.0
Requires-Dist: cryptography >=2.1
Requires-Dist: netaddr >=0.7.18
Requires-Dist: oslo.concurrency >=3.26.0
Requires-Dist: oslo.config >=5.2.0
Requires-Dist: oslo.log >=3.36.0
Requires-Dist: stestr >=1.0.0
Requires-Dist: oslo.serialization !=2.19.1,>=2.18.0
Requires-Dist: oslo.utils >=7.0.0
Requires-Dist: fixtures >=3.0.0
Requires-Dist: PyYAML >=3.12
Requires-Dist: python-subunit >=1.0.0
Requires-Dist: stevedore >=1.20.0
Requires-Dist: PrettyTable >=0.7.1
Requires-Dist: urllib3 >=1.21.1
Requires-Dist: debtcollector >=1.2.0
Requires-Dist: defusedxml >=0.7.1
Requires-Dist: fasteners >=0.16.0
Requires-Dist: testscenarios >=0.5.0
